mcp_feedback_enhanced/__init__.py
mcp_feedback_enhanced/__main__.py
mcp_feedback_enhanced/debug.py
mcp_feedback_enhanced/i18n.py
mcp_feedback_enhanced/py.typed
mcp_feedback_enhanced/server.py
mcp_feedback_enhanced/desktop_app/__init__.py
mcp_feedback_enhanced/desktop_app/desktop_app.py
mcp_feedback_enhanced/desktop_release/__init__.py
mcp_feedback_enhanced/desktop_release/mcp-feedback-enhanced-desktop-linux
mcp_feedback_enhanced/desktop_release/mcp-feedback-enhanced-desktop-macos-arm64
mcp_feedback_enhanced/desktop_release/mcp-feedback-enhanced-desktop-macos-intel
mcp_feedback_enhanced/desktop_release/mcp-feedback-enhanced-desktop.exe
mcp_feedback_enhanced/utils/__init__.py
mcp_feedback_enhanced/utils/error_handler.py
mcp_feedback_enhanced/utils/memory_monitor.py
mcp_feedback_enhanced/utils/resource_manager.py
mcp_feedback_enhanced/web/__init__.py
mcp_feedback_enhanced/web/main.py
mcp_feedback_enhanced/web/constants/__init__.py
mcp_feedback_enhanced/web/constants/message_codes.py
mcp_feedback_enhanced/web/locales/en/translation.json
mcp_feedback_enhanced/web/locales/zh-CN/translation.json
mcp_feedback_enhanced/web/locales/zh-TW/translation.json
mcp_feedback_enhanced/web/models/__init__.py
mcp_feedback_enhanced/web/models/feedback_result.py
mcp_feedback_enhanced/web/models/feedback_session.py
mcp_feedback_enhanced/web/routes/__init__.py
mcp_feedback_enhanced/web/routes/main_routes.py
mcp_feedback_enhanced/web/static/favicon.ico
mcp_feedback_enhanced/web/static/icon-192.png
mcp_feedback_enhanced/web/static/icon.svg
mcp_feedback_enhanced/web/static/index.html
mcp_feedback_enhanced/web/static/css/audio-management.css
mcp_feedback_enhanced/web/static/css/notification-settings.css
mcp_feedback_enhanced/web/static/css/prompt-management.css
mcp_feedback_enhanced/web/static/css/session-management.css
mcp_feedback_enhanced/web/static/css/styles.css
mcp_feedback_enhanced/web/static/js/app.js
mcp_feedback_enhanced/web/static/js/i18n.js
iflow_mcp_mcp_feedback_enhanced-2.6.0.dist-info/METADATA
iflow_mcp_mcp_feedback_enhanced-2.6.0.dist-info/WHEEL
iflow_mcp_mcp_feedback_enhanced-2.6.0.dist-info/entry_points.txt
iflow_mcp_mcp_feedback_enhanced-2.6.0.dist-info/licenses/LICENSE
iflow_mcp_mcp_feedback_enhanced-2.6.0.dist-info/RECORD
